{
  "workspaceCompat": {
    "ssh": {
      "testRepo": "git@github.com:wildsmith/simplej-plugin.git"
    },
    "java": {
      "home": "/Applications/Android Studio.app/Contents/jbr/Contents/Home",
      "version": {
        "major": 17
      }
    },
    "android": {
      "buildTools": {
        "major": 35,
        "minor": 0,
        "patch": 0
      }
    }
  },
  "webBrowserMappings": {
    "fileMappings": {
      "README.md": "https://github.com/wildsmith/simplej-plugin/blob/main/README.md",
      "plugin/src/main/kotlin/com/simplej/plugin/actions/settings/SimpleJSettingsConfigurable.kt": "https://plugins.jetbrains.com/docs/intellij/kotlin-ui-dsl-version-2.html#cellbind"
    }
  },
  "newModuleTemplates": [
    {
      "name": "SimpleJ Java Module",
      "files": [
        {
          "relativePath": "build.gradle.kts",
          "templateLocation": "simplej-java-module/build.gradle.kts"
        }
      ]
    },
    {
      "name": "Java Module",
      "files": [
        {
          "relativePath": "build.gradle.kts",
          "templateLocation": "java-module/build.gradle.kts"
        }
      ]
    }
  ]
}